snacli/__init__.py
snacli/snacli.py
snacli-1.2.dist-info/LICENSE.txt
snacli-1.2.dist-info/METADATA
snacli-1.2.dist-info/WHEEL
snacli-1.2.dist-info/top_level.txt
snacli-1.2.dist-info/RECORD
