Metadata-Version: 2.1
Name: snacli
Version: 1.2
Summary: Simplify writing dual use scripts for CLI and Snakemake
Home-page: https://github.com/ggonnella/snacli
Author: Giorgio Gonnella
Author-email: gonnella@zbh.uni-hamburg.de
License: ISC
Keywords: scripts,snakemake,cli,docopt
Classifier: Development Status :: 5 - Production/Stable
Classifier: Environment :: Console
Classifier: Intended Audience :: Developers
Classifier: Intended Audience :: End Users/Desktop
Classifier: Intended Audience :: Science/Research
Classifier: License :: OSI Approved :: ISC License (ISCL)
Classifier: Operating System :: MacOS :: MacOS X
Classifier: Operating System :: POSIX :: Linux
Classifier: Programming Language :: Python :: 3 :: Only
Classifier: Topic :: Software Development :: Libraries
License-File: LICENSE.txt
Requires-Dist: docopt
Requires-Dist: snakemake
